readabform/__init__.py
readabform/main.py
readabform-1.0.dist-info/METADATA
readabform-1.0.dist-info/WHEEL
readabform-1.0.dist-info/top_level.txt
readabform-1.0.dist-info/RECORD
