Metadata-Version: 2.1
Name: readabform
Version: 1.0
Author: Torrez
Requires: bestErrors
